{
  "name": "@wiris/mathtype-ckeditor4",
  "version": "@version@",
  "description": "MathType Web for CKEditor4 editor",
  "keywords": [
    "ckeditor",
    "ckeditor4",
    "chem",
    "chemistry",
    "chemtype",
    "editor",
    "equation",
    "latex",
    "math",
    "maths",
    "mathml",
    "mathtype",
    "wiris"
  ],
  "homepage" : "http://www.wiris.com/",
  "bugs" : {
    "email" : "support@wiris.com"
  },
  "author" : "WIRIS Team (http://www.wiris.com)",
  "license" : "GPL-3.0",
  "files": [
    "core/icons",
    "core/tutorials",
    "core/styles.css",
    "core/styles.src.css",
    "icons",
    "languages"
  ],
  "main": "plugin.js"
}
